odoo8_addon_sale_start_end_dates-8.0.0.1.0.99.dev20-py3.8-nspkg.pth
odoo_addons/sale_start_end_dates/README.rst
odoo_addons/sale_start_end_dates/__init__.py
odoo_addons/sale_start_end_dates/__openerp__.py
odoo_addons/sale_start_end_dates/sale.py
odoo_addons/sale_start_end_dates/sale_demo.xml
odoo_addons/sale_start_end_dates/sale_view.xml
odoo_addons/sale_start_end_dates/i18n/ca.po
odoo_addons/sale_start_end_dates/i18n/ca_ES.po
odoo_addons/sale_start_end_dates/i18n/de.po
odoo_addons/sale_start_end_dates/i18n/es.po
odoo_addons/sale_start_end_dates/i18n/es_ES.po
odoo_addons/sale_start_end_dates/i18n/fi.po
odoo_addons/sale_start_end_dates/i18n/fr.po
odoo_addons/sale_start_end_dates/i18n/hr.po
odoo_addons/sale_start_end_dates/i18n/hu.po
odoo_addons/sale_start_end_dates/i18n/it.po
odoo_addons/sale_start_end_dates/i18n/nl.po
odoo_addons/sale_start_end_dates/i18n/nl_NL.po
odoo_addons/sale_start_end_dates/i18n/pt_BR.po
odoo_addons/sale_start_end_dates/i18n/ro.po
odoo_addons/sale_start_end_dates/i18n/sale_start_end_dates.pot
odoo_addons/sale_start_end_dates/i18n/sk.po
odoo_addons/sale_start_end_dates/i18n/sl.po
odoo_addons/sale_start_end_dates/i18n/tr.po
odoo_addons/sale_start_end_dates/i18n/tr_TR.po
odoo_addons/sale_start_end_dates/i18n/zh_CN.po
odoo_addons/sale_start_end_dates/static/description/icon.png
odoo8_addon_sale_start_end_dates-8.0.0.1.0.99.dev20.dist-info/METADATA
odoo8_addon_sale_start_end_dates-8.0.0.1.0.99.dev20.dist-info/WHEEL
odoo8_addon_sale_start_end_dates-8.0.0.1.0.99.dev20.dist-info/namespace_packages.txt
odoo8_addon_sale_start_end_dates-8.0.0.1.0.99.dev20.dist-info/top_level.txt
odoo8_addon_sale_start_end_dates-8.0.0.1.0.99.dev20.dist-info/RECORD
